gempaterkini/__init__.py
earthquake_idbmkg-0.0.2.dist-info/LICENSE
earthquake_idbmkg-0.0.2.dist-info/METADATA
earthquake_idbmkg-0.0.2.dist-info/WHEEL
earthquake_idbmkg-0.0.2.dist-info/top_level.txt
earthquake_idbmkg-0.0.2.dist-info/RECORD
