Metadata-Version: 2.1
Name: earthquake-idbmkg
Version: 0.0.2
Summary: This package will get the latest eartquake data from BMKG | Indonesia Meteorological, Climatological, and Geophysical Agency
Home-page: https://github.com/coach-of-kopycode/realtime-indonesia-earthquake
Author: Todi Rahmat
Author-email: todirahmat123@gmail.com
Project-URL: Website, https://todikun.github.io/
Classifier: Programming Language :: Python :: 3
Classifier: License :: OSI Approved :: GNU General Public License v3 (GPLv3)
Classifier: Operating System :: OS Independent
Classifier: Development Status :: 5 - Production/Stable
Requires-Python: >=3.6
License-File: LICENSE
